Workbook

Sheet README
B1: GoLuQ — Digital Employee Pricing & Margin Model
B3: PURPOSE: Set profitable, India-attractive prices for each Digital Employee while funding the affiliate program.
B5: THE MODEL (every price splits three ways, as a % of PRICE — not of cost):
B6: Price = COGS (infra + ops) + Affiliate commission + Founder margin
B7: • Affiliate: 35% of price for months 1–12, then 12% lifetime (taper).
B8: • Founder: whatever is left. Floor is ~15% in Year 1; it EXPANDS to ~40–55% from month 13 as the affiliate share drops.
B9: • So the rule is: keep true COGS at or below ~50% of price (simple text employees) and ~30–35% (voice / premium).
B11: HOW TO USE:
B12: 1. Open "Cost Model" — these are ESTIMATES. Replace BLUE cells with your real vendor quotes (LLM, telephony minutes, number rental).
B13: 2. "Pricing" recomputes a suggested price from your target margin, then you set an attractive LIST price; it shows the real split.
B14: 3. "Scenarios" projects affiliate earnings AND your founder profit for any number of referred customers.
B16: COLOR KEY: Blue = your inputs (change these) · Black = formulas · Green = pulled from another sheet · Yellow = key assumption.
... B22: vendors before publishing prices. This is a planning model, not an accounting record, and not tax advice.

Sheet Cost Model
A1: Cost Model — estimated COGS per customer (₹/month)
A2: Replace blue cells with real vendor quotes. Total COGS auto-sums.
A4: Plan | B4: LLM / Processing | C4: WhatsApp (Baileys) | D4: Telephony / Voice | E4: Number Rental | F4: Hosting | G4: Support / Ops | H4: Total COGS (₹/mo)
A5: Digital Receptionist (text/WhatsApp) | B5: 200 | C5: 0 | D5: 0 | E5: 0 | F5: 50 | G5: 50 | H5: =SUM(B5:G5) -> 300
A6: Digital Customer Support (text/WhatsApp) | B6: 250 | C6: 0 | D6: 0 | E6: 0 | F6: 50 | G6: 50 | H6: =SUM(B6:G6) -> 350
A7: Digital Sales (WhatsApp + light outreach) | B7: 300 | C7: 0 | D7: 50 | E7: 0 | F7: 50 | G7: 50 | H7: =SUM(B7:G7) -> 450
A8: Digital Voice Calling — Lite (capped mins) | B8: 350 | C8: 0 | D8: 1100 | E8: 150 | F8: 50 | G8: 50 | H8: =SUM(B8:G8) -> 1700
A9: Digital Voice Calling — Pro | B9: 450 | C9: 0 | D9: 1800 | E9: 500 | F9: 100 | G9: 100 | H9: =SUM(B9:G9) -> 2950
A10: Complete Digital Workforce (3–5, incl. voice) | B10: 600 | C10: 0 | D10: 1800 | E10: 500 | F10: 150 | G10: 150 | H10: =SUM(B10:G10) -> 3200
A12: Note: Baileys = runs on the customer's own WhatsApp number → no Meta per-message fees. Voice cost dominates premium plans.
A13: Estimates as of 2026 — verify with vendors.

Sheet Pricing
A1: Pricing & Margin Split
A2: Affiliate % is of PRICE. Founder margin is the remainder (Year-1 floor ~15%, expands lifetime as affiliate tapers).
A3: Affiliate rate — Year 1 (months 1–12): | D3: 0.35
A4: Affiliate rate — Lifetime (month 13+): | D4: 0.12
A6: Plan | B6: COGS | C6: Target GM % | D6: Suggested Price | E6: LIST PRICE | F6: Actual GM % | G6: Affiliate Y1 (35%) | H6: Founder Y1 ₹ | I6: Founder Y1 % | J6: Affiliate Life (12%) | K6: Founder Life ₹ | L6: Founder Life % | M6: Annual (pay 10) | N6: Human Salary ≈ | O6: Price vs Human
A7: Digital Receptionist (text/WhatsApp) | B7: ='Cost Model'!H5 -> 300 | C7: 0.6 | D7: =B7/(1-C7) -> 750 | E7: 799 | F7: =(E7-B7)/E7 -> 0.62453066 | G7: =E7*$D$3 -> 279.65 | H7: =E7-B7-G7 -> 219.35 | I7: =H7/E7 -> 0.27453066 | J7: =E7*$D$4 -> 95.88 | K7: =E7-B7-J7 -> 403.12 | L7: =K7/E7 -> 0.50453066 | M7: =E7*10 -> 7990 | N7: 12000 | O7: =E7/N7 -> 0.066583333
A8: Digital Customer Support (text/WhatsApp) | B8: ='Cost Model'!H6 -> 350 | C8: 0.62 | D8: =B8/(1-C8) -> 921.05263 | E8: 999 | F8: =(E8-B8)/E8 -> 0.64964965 | G8: =E8*$D$3 -> 349.65 | H8: =E8-B8-G8 -> 299.35 | I8: =H8/E8 -> 0.29964965 | J8: =E8*$D$4 -> 119.88 | K8: =E8-B8-J8 -> 529.12 | L8: =K8/E8 -> 0.52964965 | M8: =E8*10 -> 9990 | N8: 15000 | O8: =E8/N8 -> 0.0666
A9: Digital Sales (WhatsApp + light outreach) | B9: ='Cost Model'!H7 -> 450 | C9: 0.65 | D9: =B9/(1-C9) -> 1285.7143 | E9: 1499 | F9: =(E9-B9)/E9 -> 0.69979987 | G9: =E9*$D$3 -> 524.65 | H9: =E9-B9-G9 -> 524.35 | I9: =H9/E9 -> 0.34979987 | J9: =E9*$D$4 -> 179.88 | K9: =E9-B9-J9 -> 869.12 | L9: =K9/E9 -> 0.57979987 | M9: =E9*10 -> 14990 | N9: 18000 | O9: =E9/N9 -> 0.083277778
A10: Digital Voice Calling — Lite (capped mins) | B10: ='Cost Model'!H8 -> 1700 | C10: 0.68 | D10: =B10/(1-C10) -> 5312.5 | E10: 4999 | F10: =(E10-B10)/E10 -> 0.65993199 | G10: =E10*$D$3 -> 1749.65 | H10: =E10-B10-G10 -> 1549.35 | I10: =H10/E10 -> 0.30993199 | J10: =E10*$D$4 -> 599.88 | K10: =E10-B10-J10 -> 2699.12 | L10: =K10/E10 -> 0.53993199 | M10: =E10*10 -> 49990 | N10: 15000 | O10: =E10/N10 -> 0.33326667
A11: Digital Voice Calling — Pro | B11: ='Cost Model'!H9 -> 2950 | C11: 0.59 | D11: =B11/(1-C11) -> 7195.122 | E11: 6999 | F11: =(E11-B11)/E11 -> 0.57851122 | G11: =E11*$D$3 -> 2449.65 | H11: =E11-B11-G11 -> 1599.35 | I11: =H11/E11 -> 0.22851122 | J11: =E11*$D$4 -> 839.88 | K11: =E11-B11-J11 -> 3209.12 | L11: =K11/E11 -> 0.45851122 | M11: =E11*10 -> 69990 | N11: 15000 | O11: =E11/N11 -> 0.4666
A12: Complete Digital Workforce (3–5, incl. voice) | B12: ='Cost Model'!H10 -> 3200 | C12: 0.65 | D12: =B12/(1-C12) -> 9142.8571 | E12: 9999 | F12: =(E12-B12)/E12 -> 0.679968 | G12: =E12*$D$3 -> 3499.65 | H12: =E12-B12-G12 -> 3299.35 | I12: =H12/E12 -> 0.329968 | J12: =E12*$D$4 -> 1199.88 | K12: =E12-B12-J12 -> 5599.12 | L12: =K12/E12 -> 0.559968 | M12: =E12*10 -> 99990 | N12: 50000 | O12: =E12/N12 -> 0.19998
A14: Travel & tours (cab/agency) businesses buy the Receptionist or Support plan (₹799–₹999) — the 2am-booking WhatsApp employee.
A15: "Price vs Human" shows you charge a small fraction of a human salary — the ₹200-value-for-₹100 story for the sales pitch.

Sheet Scenarios
A1: Affiliate Earnings & Founder Profit — Scenario
A2: Change the three blue inputs to model any deal. Affiliate rates pull from the Pricing sheet.
A4: Plan price (₹/mo) | B4: 1499
A5: Plan COGS (₹/mo) | B5: 450
A6: Customers referred (N) | B6: 10
A8: AFFILIATE EARNINGS
A9: Affiliate income — Year 1 (₹/month) | B9: =B4*Pricing!$D$3*B6 -> 5246.5
A10: Affiliate income — Year 1 total (12 mo) | B10: =B4*Pricing!$D$3*B6*12 -> 62958
A11: Affiliate income — Month 13+ (₹/month, lifetime) | B11: =B4*Pricing!$D$4*B6 -> 1798.8
A12: Affiliate income — 24-month cumulative | B12: =B4*Pricing!$D$3*B6*12 + B4*Pricing!$D$4*B6*12 -> 84543.6
A14: FOUNDER PROFIT (after COGS + affiliate)
A15: Founder profit — Year 1 (₹/month) | B15: =(B4-B5-B4*Pricing!$D$3)*B6 -> 5243.5
A16: Founder profit — Year 1 total (12 mo) | B16: =(B4-B5-B4*Pricing!$D$3)*B6*12 -> 62922
A17: Founder profit — Month 13+ (₹/month, lifetime) | B17: =(B4-B5-B4*Pricing!$D$4)*B6 -> 8691.2
A18: Founder profit — 24-month cumulative | B18: =(B4-B5-B4*Pricing!$D$3)*B6*12 + (B4-B5-B4*Pricing!$D$4)*B6*12 -> 167216.4
A21: QUICK REFERENCE — per single customer, by plan
A22: Plan | B22: List Price | C22: Affiliate Y1 total | D22: Affiliate ₹/mo (life) | E22: Founder Y1 ₹/mo | F22: Founder ₹/mo (life)
A23: =Pricing!A7 -> Digital Receptionist (text/WhatsApp) | B23: =Pricing!E7 -> 799 | C23: =Pricing!E7*Pricing!$D$3*12 -> 3355.8 | D23: =Pricing!J7 -> 95.88 | E23: =Pricing!H7 -> 219.35 | F23: =Pricing!K7 -> 403.12
A24: =Pricing!A8 -> Digital Customer Support (text/WhatsApp) | B24: =Pricing!E8 -> 999 | C24: =Pricing!E8*Pricing!$D$3*12 -> 4195.8 | D24: =Pricing!J8 -> 119.88 | E24: =Pricing!H8 -> 299.35 | F24: =Pricing!K8 -> 529.12
A25: =Pricing!A9 -> Digital Sales (WhatsApp + light outreach) | B25: =Pricing!E9 -> 1499 | C25: =Pricing!E9*Pricing!$D$3*12 -> 6295.8 | D25: =Pricing!J9 -> 179.88 | E25: =Pricing!H9 -> 524.35 | F25: =Pricing!K9 -> 869.12
A26: =Pricing!A10 -> Digital Voice Calling — Lite (capped mins) | B26: =Pricing!E10 -> 4999 | C26: =Pricing!E10*Pricing!$D$3*12 -> 20995.8 | D26: =Pricing!J10 -> 599.88 | E26: =Pricing!H10 -> 1549.35 | F26: =Pricing!K10 -> 2699.12
A27: =Pricing!A11 -> Digital Voice Calling — Pro | B27: =Pricing!E11 -> 6999 | C27: =Pricing!E11*Pricing!$D$3*12 -> 29395.8 | D27: =Pricing!J11 -> 839.88 | E27: =Pricing!H11 -> 1599.35 | F27: =Pricing!K11 -> 3209.12
A28: =Pricing!A12 -> Complete Digital Workforce (3–5, incl. voice) | B28: =Pricing!E12 -> 9999 | C28: =Pricing!E12*Pricing!$D$3*12 -> 41995.8 | D28: =Pricing!J12 -> 1199.88 | E28: =Pricing!H12 -> 3299.35 | F28: =Pricing!K12 -> 5599.12

Sheet Fair-Use Caps
A1: Fair-Use Caps — worst-case COGS ceiling per plan
A2: Caps bound the cost of a high-traffic customer. Columns prove the founder margin stays healthy EVEN AT FULL CAP.
A3: Enforced in the Digital Employee runtime (not the website). Past the cap → graceful handoff + owner alert + upgrade/overage. See spec §16.
A5: Plan | B5: Metered unit | C5: Included cap / mo | D5: Cost / unit | E5: Variable COGS at cap | F5: Fixed COGS / mo | G5: Total COGS at cap | H5: List price | I5: GM at cap | J5: Affiliate Y1 | K5: Founder Y1 at cap | L5: Founder Y1 % | M5: Overage / unit
A6: Digital Receptionist | B6: conversations | C6: 1500 | D6: 0.15 | E6: =C6*D6 -> 225 | F6: 100 | G6: =E6+F6 -> 325 | H6: =Pricing!E7 -> 799 | I6: =(H6-G6)/H6 -> 0.59324155 | J6: =H6*Pricing!$D$3 -> 279.65 | K6: =H6-G6-J6 -> 194.35 | L6: =K6/H6 -> 0.24324155 | M6: 0.5
A7: Digital Customer Support | B7: conversations | C7: 2000 | D7: 0.15 | E7: =C7*D7 -> 300 | F7: 100 | G7: =E7+F7 -> 400 | H7: =Pricing!E8 -> 999 | I7: =(H7-G7)/H7 -> 0.5995996 | J7: =H7*Pricing!$D$3 -> 349.65 | K7: =H7-G7-J7 -> 249.35 | L7: =K7/H7 -> 0.2495996 | M7: 0.5
A8: Digital Sales | B8: conversations | C8: 3000 | D8: 0.15 | E8: =C8*D8 -> 450 | F8: 200 | G8: =E8+F8 -> 650 | H8: =Pricing!E9 -> 1499 | I8: =(H8-G8)/H8 -> 0.56637759 | J8: =H8*Pricing!$D$3 -> 524.65 | K8: =H8-G8-J8 -> 324.35 | L8: =K8/H8 -> 0.21637759 | M8: 0.5
A9: Voice Calling — Lite | B9: call minutes | C9: 1200 | D9: 1 | E9: =C9*D9 -> 1200 | F9: 650 | G9: =E9+F9 -> 1850 | H9: =Pricing!E10 -> 4999 | I9: =(H9-G9)/H9 -> 0.62992599 | J9: =H9*Pricing!$D$3 -> 1749.65 | K9: =H9-G9-J9 -> 1399.35 | L9: =K9/H9 -> 0.27992599 | M9: 2.5
A10: Voice Calling — Pro | B10: call minutes | C10: 2500 | D10: 1 | E10: =C10*D10 -> 2500 | F10: 650 | G10: =E10+F10 -> 3150 | H10: =Pricing!E11 -> 6999 | I10: =(H10-G10)/H10 -> 0.54993571 | J10: =H10*Pricing!$D$3 -> 2449.65 | K10: =H10-G10-J10 -> 1399.35 | L10: =K10/H10 -> 0.19993571 | M10: 2.5
A11: Complete Workforce | B11: mins + chats* | C11: 2000 | D11: 1 | E11: =C11*D11 -> 2000 | F11: 900 | G11: =E11+F11 -> 2900 | H11: =Pricing!E12 -> 9999 | I11: =(H11-G11)/H11 -> 0.709971 | J11: =H11*Pricing!$D$3 -> 3499.65 | K11: =H11-G11-J11 -> 3599.35 | L11: =K11/H11 -> 0.359971 | M11: 2.5
A13: *Workforce bundle: ~2,000 voice minutes + ~3,000–4,000 chats; chat cost absorbed in fixed. Founder Y1% stays ≥20% on every plan at full cap.
A14: Overage policy: soft cap with ~10% buffer → owner notified → either per-unit overage billing OR one-tap upgrade to the next plan. Never a hard stop (customer always gets a reply / handoff).
A15: Confirm Cost/unit with real vendor quotes (LLM per conversation; telephony+voice per minute).
